beast_logger/__init__.py
beast_logger/apply_monkey_patch.py
beast_logger/log_json.py
beast_logger/print_basic.py
beast_logger/print_nested.py
beast_logger/print_tensor.py
beast_logger/register.py
beast_logger/serve_log_files.py
beast_logger/web_launcher.py
beast_logger-0.1.4.dist-info/licenses/LICENSE
web_display/.gitignore
web_display/README.md
web_display/go.py
web_display/install.py
web_display/package-lock.json
web_display/package.json
web_display/start_web.py
web_display/start_web.sh
web_display/start_web_fast.sh
web_display/tsconfig.json
web_display/tsconfig.server.json
web_display/public/favicon.ico
web_display/public/index.html
web_display/public/logo192.png
web_display/public/logo512.png
web_display/public/manifest.json
web_display/public/robots.txt
web_display/src/App.css
web_display/src/App.test.tsx
web_display/src/App.tsx
web_display/src/Ubuntu Mono derivative Powerline Bold.ttf
web_display/src/Ubuntu Mono derivative Powerline.ttf
web_display/src/index.css
web_display/src/index.tsx
web_display/src/logo.svg
web_display/src/react-app-env.d.ts
web_display/src/reportWebVitals.ts
web_display/src/setupTests.ts
web_display/src/types.ts
web_display/src/components/DisplayToggleWrapper.tsx
web_display/src/components/EntryViewer.tsx
web_display/src/components/LogFileList.tsx
web_display/src/components/LogViewer.tsx
web_display/src/components/NestedEntryViewer.tsx
web_display/src/components/ScrollButtons.tsx
web_display/src/components/SimpleBadge.tsx
web_display/src/server/server.ts
web_display/src/utils/logParser.ts
web_display_dist/build_pub/asset-manifest.json
web_display_dist/build_pub/favicon.ico
web_display_dist/build_pub/index.html
web_display_dist/build_pub/logo192.png
web_display_dist/build_pub/logo512.png
web_display_dist/build_pub/manifest.json
web_display_dist/build_pub/robots.txt
web_display_dist/build_pub/static/css/main.7daf22ea.css
web_display_dist/build_pub/static/css/main.7daf22ea.css.map
web_display_dist/build_pub/static/js/453.3e9ee757.chunk.js
beast_logger-0.1.4.dist-info/METADATA
beast_logger-0.1.4.dist-info/WHEEL
beast_logger-0.1.4.dist-info/entry_points.txt
beast_logger-0.1.4.dist-info/top_level.txt
beast_logger-0.1.4.dist-info/RECORD
