Metadata-Version: 2.4
Name: beast-logger
Version: 0.1.4
Summary: A package for advanced logging and visualization of Python objects, especially tensors.
Home-page: https://github.com/beast-logger
Author: qingxu.fu@alibaba-inc.com
Author-email: qingxu.fu@alibaba-inc.com
Project-URL: Bug Reports, https://github.com/beast-logger/issues
Project-URL: Source, https://github.com/beast-logger
Classifier: Development Status :: 3 - Alpha
Classifier: Intended Audience :: Developers
Classifier: License :: OSI Approved :: MIT License
Classifier: Operating System :: OS Independent
Classifier: Programming Language :: Python :: 3
Classifier: Programming Language :: Python :: 3.7
Classifier: Programming Language :: Python :: 3.8
Classifier: Programming Language :: Python :: 3.9
Classifier: Programming Language :: Python :: 3.10
Classifier: Programming Language :: Python :: 3.11
Classifier: Programming Language :: Python :: 3.12
Classifier: Programming Language :: Python :: 3.13
Classifier: Topic :: Software Development :: Libraries :: Python Modules
Requires-Python: >=3.7
License-File: LICENSE
Requires-Dist: loguru
Requires-Dist: rich
Requires-Dist: jieba
Requires-Dist: pydantic
Requires-Dist: fastapi
Requires-Dist: uvicorn
Dynamic: author
Dynamic: author-email
Dynamic: classifier
Dynamic: description
Dynamic: description-content-type
Dynamic: home-page
Dynamic: license-file
Dynamic: project-url
Dynamic: requires-dist
Dynamic: requires-python
Dynamic: summary
